anl/__init__.py
anl/__main__.py
anl/cli.py
anl/anl2024/__init__.py
anl/anl2024/runner.py
anl/anl2024/negotiators/__init__.py
anl/anl2024/negotiators/base.py
anl/anl2024/negotiators/builtins.p_
anl/anl2024/negotiators/builtins/__init__.py
anl/anl2024/negotiators/builtins/micro.py
anl/anl2024/negotiators/builtins/nash_seeker.py
anl/anl2024/negotiators/builtins/rv_fitter.py
anl/anl2024/negotiators/builtins/wrappers.py
anl/visualizer/app.py
anl/visualizer/cli.py
anl-0.1.13.dist-info/AUTHORS.rst
anl-0.1.13.dist-info/LICENSE
anl-0.1.13.dist-info/METADATA
anl-0.1.13.dist-info/WHEEL
anl-0.1.13.dist-info/entry_points.txt
anl-0.1.13.dist-info/top_level.txt
anl-0.1.13.dist-info/RECORD
