Metadata-Version: 2.2
Name: anl
Version: 0.1.13
Summary: ANAC Automated Negotiations League Platform
Home-page: https://github.com/autoneg/anl
Author: Yasser Mohammad
Author-email: yasserfarouk@gmail.com
Project-URL: Documentation, https://anl.readthedocs.io/
Project-URL: Changelog, https://anl.readthedocs.io/en/latest/changelog.html
Project-URL: Issue Tracker, https://github.com/autoneg/anl/issues
Classifier: Development Status :: 5 - Production/Stable
Classifier: Intended Audience :: Developers
Classifier: License :: OSI Approved :: GNU General Public License v2 or later (GPLv2+)
Classifier: Operating System :: Unix
Classifier: Operating System :: POSIX
Classifier: Operating System :: Microsoft :: Windows
Classifier: Programming Language :: Python
Classifier: Programming Language :: Python :: 3.10
Classifier: Programming Language :: Python :: 3.11
Classifier: Programming Language :: Python :: Implementation :: CPython
Classifier: Programming Language :: Python :: Implementation :: PyPy
Requires-Python: >=3.10
License-File: LICENSE
License-File: AUTHORS.rst
Requires-Dist: click
Requires-Dist: pytest
Requires-Dist: hypothesis
Requires-Dist: prettytable
Requires-Dist: negmas>=0.11.2
Requires-Dist: tqdm
Requires-Dist: joblib
Requires-Dist: jupyter
Requires-Dist: gif
Requires-Dist: streamlit
Dynamic: author
Dynamic: author-email
Dynamic: classifier
Dynamic: description
Dynamic: description-content-type
Dynamic: home-page
Dynamic: project-url
Dynamic: requires-dist
Dynamic: requires-python
Dynamic: summary
